extensions/__init__.py
extensions/idcac_2.9.8.xpi
extensions/referer_header.xpi
extensions/uBlock0_1.18.14.xpi
extensions/__pycache__/__init__.cpython-37.pyc
extensions/referer_header/main.js
extensions/referer_header/manifest.json
saas/__init__.py
saas/saas.py
saas/threads.py
saas/crawler/__init__.py
saas/crawler/crawler.py
saas/mount/__init__.py
saas/mount/file.py
saas/mount/filesystem.py
saas/photographer/__init__.py
saas/photographer/addons.py
saas/photographer/camera.py
saas/photographer/javascript.py
saas/photographer/photo.py
saas/photographer/photographer.py
saas/photographer/js/document_height.js
saas/photographer/js/image_count.js
saas/photographer/js/images_loaded.js
saas/photographer/js/images_monitor.js
saas/photographer/js/script_count.js
saas/photographer/js/scroll_y.js
saas/photographer/js/stylesheet_count.js
saas/storage/__init__.py
saas/storage/datadir.py
saas/storage/index.py
saas/storage/refresh.py
saas/utils/__init__.py
saas/utils/args.py
saas/utils/console.py
saas/utils/files.py
saas/utils/stats.py
saas/web/__init__.py
saas/web/browser.py
saas/web/page.py
saas/web/url.py
tests/__init__.py
tests/test_camera.py
tests/test_crawler.py
tests/test_filesystem.py
tests/test_index.py
tests/test_path.py
tests/test_photo.py
tests/test_photographer.py
tests/test_url.py
saas-1.2.1.dist-info/LICENSE
saas-1.2.1.dist-info/METADATA
saas-1.2.1.dist-info/WHEEL
saas-1.2.1.dist-info/entry_points.txt
saas-1.2.1.dist-info/top_level.txt
saas-1.2.1.dist-info/RECORD
