Metadata-Version: 2.1
Name: saas
Version: 1.2.1
Summary: Screenshot as a service
Home-page: https://github.com/nattvara/saas
Author: Ludwig Kristoffersson
Author-email: ludwig@kristoffersson.org
License: MIT
Platform: UNKNOWN
Requires-Python: >=3.7
Requires-Dist: wheel (==0.32.*)
Requires-Dist: beeprint (==2.4.*)
Requires-Dist: elasticsearch (==6.3.*)
Requires-Dist: fusepy (==3.0.*)
Requires-Dist: psutil (==4.3.*)
Requires-Dist: selenium
